{
  "Id": null,
  "DocumentKey": "a6b92e5e7d3ae666237826c740427ab9fb508ed6",
  "Project": {
    "Id": 1242,
    "DocumentKey": null,
    "Title": null,
    "IndustrySetId": 0,
    "CommoditySetId": 0,
    "HouseholdSetId": 0,
    "OwnerId": 0,
    "HasImpacts": false,
    "HasResults": false,
    "LastOpened": null,
    "LastImpactRunId": null,
    "UserWhoCreatedId": null,
    "UserWhoUpdatedId": null,
    "CreatedDate": null,
    "LastUpdatedDate": null,
    "IsDeleted": false,
    "DeletedDate": null,
    "IsArchived": false,
    "ArchivedDate": null
  },
  "Analyses": [],
  "Impact": {
    "Name": null,
    "ProjectId": 1242,
    "Events": [
      {
        "SpecificationCode": 65,
        "EventType": 1,
        "Output": 1000000.0,
        "Employment": null,
        "EmployeeCompensation": null,
        "ProprietorIncome": null,
        "Margins": null,
        "GdpDeflator": null,
        "OutputDeflator": null,
        "LocalPurchasePercentage": 1.0,
        "OverideValidationWarning": false,
        "HouseholdIncome": null,
        "Id": 2166,
        "ProjectId": 1242,
        "OwnerId": 0,
        "Title": "event1",
        "DocumentKey": null,
        "UserWhoCreatedId": null,
        "UserWhoUpdatedId": 1,
        "CreatedDate": null,
        "LastUpdatedDate": "2018-06-22T12:38:31.8525742Z",
        "IsDeleted": false,
        "DeletedDate": null,
        "IsArchived": false,
        "ArchivedDate": null
      }
    ],
    "Groups": [
      {
        "ModelId": 211,
        "Year": 38,
        "Events": [
          {
            "SpecificationCode": 65,
            "EventType": 1,
            "Output": 1000000.0,
            "Employment": null,
            "EmployeeCompensation": null,
            "ProprietorIncome": null,
            "Margins": null,
            "GdpDeflator": null,
            "OutputDeflator": null,
            "LocalPurchasePercentage": 1.0,
            "OverideValidationWarning": false,
            "HouseholdIncome": null,
            "Id": 2166,
            "ProjectId": 1242,
            "OwnerId": 0,
            "Title": "event1",
            "DocumentKey": null,
            "UserWhoCreatedId": null,
            "UserWhoUpdatedId": 1,
            "CreatedDate": null,
            "LastUpdatedDate": "2018-06-19T05:37:57.4009544Z",
            "IsDeleted": false,
            "DeletedDate": null,
            "IsArchived": false,
            "ArchivedDate": null
          }
        ],
        "AnalysisId": null,
        "Id": 2227,
        "ProjectId": 1242,
        "OwnerId": 0,
        "Title": "Wash-MN",
        "DocumentKey": null,
        "UserWhoCreatedId": null,
        "UserWhoUpdatedId": 1,
        "CreatedDate": "2018-06-18T06:27:47.1988129Z",
        "LastUpdatedDate": "2018-06-22T12:38:31.8525747Z",
        "IsDeleted": false,
        "DeletedDate": null,
        "IsArchived": false,
        "ArchivedDate": null
      },
      {
        "ModelId": 218,
        "Year": 38,
        "Events": [
          {
            "SpecificationCode": 65,
            "EventType": 1,
            "Output": 1000000.0,
            "Employment": null,
            "EmployeeCompensation": null,
            "ProprietorIncome": null,
            "Margins": null,
            "GdpDeflator": null,
            "OutputDeflator": null,
            "LocalPurchasePercentage": 1.0,
            "OverideValidationWarning": false,
            "HouseholdIncome": null,
            "Id": 2166,
            "ProjectId": 1242,
            "OwnerId": 0,
            "Title": "event1",
            "DocumentKey": null,
            "UserWhoCreatedId": null,
            "UserWhoUpdatedId": 1,
            "CreatedDate": null,
            "LastUpdatedDate": "2018-06-19T05:37:57.4009544Z",
            "IsDeleted": false,
            "DeletedDate": null,
            "IsArchived": false,
            "ArchivedDate": null
          }
        ],
        "AnalysisId": null,
        "Id": 2294,
        "ProjectId": 1242,
        "OwnerId": 0,
        "Title": "NC+York-SC",
        "DocumentKey": null,
        "UserWhoCreatedId": null,
        "UserWhoUpdatedId": 1,
        "CreatedDate": null,
        "LastUpdatedDate": "2018-06-22T12:38:31.852575Z",
        "IsDeleted": false,
        "DeletedDate": null,
        "IsArchived": false,
        "ArchivedDate": null
      }
    ]
  },
  "IsArchived": false,
  "ArchivedDateTime": null,
  "SharedDatetimes": [],
  "LastOpenedDate": "0001-01-01T00:00:00"
}