{"Id":null,"DocumentKey":"33e580ea041f2da488256c7992acccaf68fe6652","Project":{"Id":578,"DocumentKey":null,"Title":null,"IndustrySetId":0,"CommoditySetId":0,"HouseholdSetId":0,"OwnerId":0,"HasImpacts":false,"HasResults":false,"LastOpened":null,"LastImpactRunId":null,"UserWhoCreatedId":null,"UserWhoUpdatedId":null,"CreatedDate":null,"LastUpdatedDate":null,"IsDeleted":false,"DeletedDate":null,"IsArchived":false,"ArchivedDate":null},"Analyses":[],"Impact":{"Name":null,"ProjectId":578,"Events":[],"Groups":[{"ModelId":-1926852216,"Year":38,"Events":[],"AnalysisId":null,"Id":1049,"ProjectId":578,"OwnerId":0,"Title":"Nevada group","DocumentKey":null,"UserWhoCreatedId":null,"UserWhoUpdatedId":1,"CreatedDate":"2018-04-25T18:09:39.0525711Z","LastUpdatedDate":"2018-05-10T12:09:39.9669249Z","IsDeleted":false,"DeletedDate":null,"IsArchived":false,"ArchivedDate":null}]},"IsArchived":false,"ArchivedDateTime":null,"SharedDatetimes":[],"LastOpenedDate":"0001-01-01T00:00:00"}