{"Id":null,"DocumentKey":"6f7ad0fb3ad708634fbc6539575beafbce3c5bd2","Project":{"Id":790,"DocumentKey":null,"Title":null,"IndustrySetId":0,"CommoditySetId":0,"HouseholdSetId":0,"OwnerId":0,"HasImpacts":false,"HasResults":false,"LastOpened":null,"LastImpactRunId":null,"UserWhoCreatedId":null,"UserWhoUpdatedId":null,"CreatedDate":null,"LastUpdatedDate":null,"IsDeleted":false,"DeletedDate":null,"IsArchived":false,"ArchivedDate":null},"Analyses":[],"Impact":{"Name":null,"ProjectId":790,"Events":[{"SpecificationCode":52,"EventType":1,"Output":100000000.0,"Employment":null,"EmployeeCompensation":null,"ProprietorIncome":null,"Margins":null,"GdpDeflator":null,"OutputDeflator":null,"LocalPurchasePercentage":1.0,"OverideValidationWarning":false,"HouseholdIncome":null,"Id":1320,"ProjectId":790,"OwnerId":0,"Title":"Construction","DocumentKey":null,"UserWhoCreatedId":null,"UserWhoUpdatedId":1,"CreatedDate":null,"LastUpdatedDate":"2018-05-14T19:07:20.0903405Z","IsDeleted":false,"DeletedDate":null,"IsArchived":false,"ArchivedDate":null}],"Groups":[{"ModelId":-437556056,"Year":38,"Events":[],"AnalysisId":null,"Id":1489,"ProjectId":790,"OwnerId":0,"Title":"North Carolina group","DocumentKey":null,"UserWhoCreatedId":null,"UserWhoUpdatedId":1,"CreatedDate":"2018-05-14T19:06:43.9089744Z","LastUpdatedDate":"2018-05-14T19:07:20.0903411Z","IsDeleted":false,"DeletedDate":null,"IsArchived":false,"ArchivedDate":null},{"ModelId":-101559749,"Year":38,"Events":[],"AnalysisId":null,"Id":1490,"ProjectId":790,"OwnerId":0,"Title":"South Carolina group","DocumentKey":null,"UserWhoCreatedId":null,"UserWhoUpdatedId":1,"CreatedDate":null,"LastUpdatedDate":"2018-05-14T19:07:20.0903414Z","IsDeleted":false,"DeletedDate":null,"IsArchived":false,"ArchivedDate":null},{"ModelId":-378348887,"Year":38,"Events":[],"AnalysisId":null,"Id":1491,"ProjectId":790,"OwnerId":0,"Title":"Georgia group","DocumentKey":null,"UserWhoCreatedId":null,"UserWhoUpdatedId":1,"CreatedDate":null,"LastUpdatedDate":"2018-05-14T19:07:20.0903417Z","IsDeleted":false,"DeletedDate":null,"IsArchived":false,"ArchivedDate":null}]},"IsArchived":false,"ArchivedDateTime":null,"SharedDatetimes":[],"LastOpenedDate":"0001-01-01T00:00:00"}