{
  "Id": null,
  "DocumentKey": "16a1df0d089c67d3cf50fccef4feec0121876d91",
  "Project": {
    "Id": 1357,
    "DocumentKey": null,
    "Title": null,
    "IndustrySetId": 0,
    "CommoditySetId": 0,
    "HouseholdSetId": 0,
    "OwnerId": 0,
    "HasImpacts": false,
    "HasResults": false,
    "LastOpened": null,
    "LastImpactRunId": null,
    "UserWhoCreatedId": null,
    "UserWhoUpdatedId": null,
    "CreatedDate": null,
    "LastUpdatedDate": null,
    "IsDeleted": false,
    "DeletedDate": null,
    "IsArchived": false,
    "ArchivedDate": null
  },
  "Analyses": [],
  "Impact": {
    "Name": null,
    "ProjectId": 1357,
    "Events": [
      {
        "SpecificationCode": 5001,
        "EventType": 6,
        "Output": null,
        "Employment": null,
        "EmployeeCompensation": 15000000.0,
        "ProprietorIncome": null,
        "Margins": false,
        "GdpDeflator": null,
        "OutputDeflator": null,
        "LocalPurchasePercentage": 1.0,
        "OverideValidationWarning": false,
        "HouseholdIncome": null,
        "Id": 2397,
        "ProjectId": 1357,
        "OwnerId": 0,
        "Title": "Ev_WMN_LI_EC_v2",
        "DocumentKey": null,
        "UserWhoCreatedId": null,
        "UserWhoUpdatedId": 1,
        "CreatedDate": null,
        "LastUpdatedDate": "2018-06-29T06:03:48.5707676Z",
        "IsDeleted": false,
        "DeletedDate": null,
        "IsArchived": false,
        "ArchivedDate": null
      },
      {
        "SpecificationCode": 6001,
        "EventType": 6,
        "Output": null,
        "Employment": null,
        "EmployeeCompensation": null,
        "ProprietorIncome": 1500000.0,
        "Margins": false,
        "GdpDeflator": null,
        "OutputDeflator": null,
        "LocalPurchasePercentage": 1.0,
        "OverideValidationWarning": false,
        "HouseholdIncome": null,
        "Id": 2398,
        "ProjectId": 1357,
        "OwnerId": 0,
        "Title": "Ev_WMN_LI_PI_v2",
        "DocumentKey": null,
        "UserWhoCreatedId": null,
        "UserWhoUpdatedId": 1,
        "CreatedDate": null,
        "LastUpdatedDate": "2018-06-29T06:03:48.5707681Z",
        "IsDeleted": false,
        "DeletedDate": null,
        "IsArchived": false,
        "ArchivedDate": null
      }
    ],
    "Groups": [
      {
        "ModelId": 206,
        "Year": 38,
        "Events": [
          {
            "SpecificationCode": 6001,
            "EventType": 6,
            "Output": null,
            "Employment": null,
            "EmployeeCompensation": null,
            "ProprietorIncome": 1500000.0,
            "Margins": false,
            "GdpDeflator": null,
            "OutputDeflator": null,
            "LocalPurchasePercentage": 1.0,
            "OverideValidationWarning": false,
            "HouseholdIncome": null,
            "Id": 2398,
            "ProjectId": 1357,
            "OwnerId": 0,
            "Title": "Ev_WMN_LI_PI_v2",
            "DocumentKey": null,
            "UserWhoCreatedId": null,
            "UserWhoUpdatedId": null,
            "CreatedDate": null,
            "LastUpdatedDate": null,
            "IsDeleted": false,
            "DeletedDate": null,
            "IsArchived": false,
            "ArchivedDate": null
          }
        ],
        "AnalysisId": null,
        "Id": 2393,
        "ProjectId": 1357,
        "OwnerId": 0,
        "Title": "Gp2",
        "DocumentKey": null,
        "UserWhoCreatedId": null,
        "UserWhoUpdatedId": 1,
        "CreatedDate": "2018-06-29T05:10:29.731009Z",
        "LastUpdatedDate": "2018-06-29T06:03:48.5707685Z",
        "IsDeleted": false,
        "DeletedDate": null,
        "IsArchived": false,
        "ArchivedDate": null
      }
    ]
  },
  "IsArchived": false,
  "ArchivedDateTime": null,
  "SharedDatetimes": [],
  "LastOpenedDate": "0001-01-01T00:00:00"
}