{"Id":null,"DocumentKey":"","Project":{"Id":303,"DocumentKey":"","Title":"Created from regions","IndustrySetId":2,"CommoditySetId":1,"HouseholdSetId":1,"OwnerId":1,"HasImpacts":false,"HasResults":false,"LastOpened":null,"LastImpactRunId":null,"UserWhoCreatedId":1,"UserWhoUpdatedId":1,"CreatedDate":"2018-04-16T11:53:38","LastUpdatedDate":"2018-04-16T11:53:38","IsDeleted":false,"DeletedDate":null,"IsArchived":false,"ArchivedDate":null},"Analyses":[],"Impact":{"Name":"Impact from Regions","ProjectId":303,"Events":[],"Groups":[{"ModelId":-96470745,"Year":19,"Events":[],"AnalysisId":null,"Id":695,"ProjectId":303,"OwnerId":0,"Title":"Vermont group","DocumentKey":"","UserWhoCreatedId":1,"UserWhoUpdatedId":1,"CreatedDate":"2018-04-16T11:53:39.0744238Z","LastUpdatedDate":"2018-04-16T11:53:39.074424Z","IsDeleted":false,"DeletedDate":null,"IsArchived":false,"ArchivedDate":null}]},"IsArchived":false,"ArchivedDateTime":null,"SharedDatetimes":[],"LastOpenedDate":"0001-01-01T00:00:00"}