{"Id":null,"DocumentKey":"33694a1e6a300d8dd6b3bed2f941c84ed4546a5e","Project":{"Id":1051,"DocumentKey":null,"Title":null,"IndustrySetId":0,"CommoditySetId":0,"HouseholdSetId":0,"OwnerId":0,"HasImpacts":false,"HasResults":false,"LastOpened":null,"LastImpactRunId":null,"UserWhoCreatedId":null,"UserWhoUpdatedId":null,"CreatedDate":null,"LastUpdatedDate":null,"IsDeleted":false,"DeletedDate":null,"IsArchived":false,"ArchivedDate":null},"Analyses":[],"Impact":{"Name":null,"ProjectId":1051,"Events":[{"SpecificationCode":1,"EventType":4,"Output":null,"Employment":null,"EmployeeCompensation":null,"ProprietorIncome":null,"Margins":false,"GdpDeflator":null,"OutputDeflator":null,"LocalPurchasePercentage":1.0,"OverideValidationWarning":false,"HouseholdIncome":null,"Id":1809,"ProjectId":1051,"OwnerId":0,"Title":"PI_1_A","DocumentKey":null,"UserWhoCreatedId":null,"UserWhoUpdatedId":1,"CreatedDate":null,"LastUpdatedDate":"2018-06-04T12:28:04.3541398Z","IsDeleted":false,"DeletedDate":null,"IsArchived":false,"ArchivedDate":null},{"SpecificationCode":417,"EventType":4,"Output":null,"Employment":null,"EmployeeCompensation":null,"ProprietorIncome":1000000.0,"Margins":false,"GdpDeflator":null,"OutputDeflator":null,"LocalPurchasePercentage":1.0,"OverideValidationWarning":false,"HouseholdIncome":null,"Id":1811,"ProjectId":1051,"OwnerId":0,"Title":"PI_417_A","DocumentKey":null,"UserWhoCreatedId":null,"UserWhoUpdatedId":1,"CreatedDate":null,"LastUpdatedDate":"2018-06-04T12:28:04.3541402Z","IsDeleted":false,"DeletedDate":null,"IsArchived":false,"ArchivedDate":null}],"Groups":[{"ModelId":84,"Year":38,"Events":[{"SpecificationCode":417,"EventType":4,"Output":null,"Employment":null,"EmployeeCompensation":null,"ProprietorIncome":1000000.0,"Margins":false,"GdpDeflator":null,"OutputDeflator":null,"LocalPurchasePercentage":1.0,"OverideValidationWarning":false,"HouseholdIncome":null,"Id":1811,"ProjectId":1051,"OwnerId":0,"Title":"PI_417_A","DocumentKey":null,"UserWhoCreatedId":null,"UserWhoUpdatedId":null,"CreatedDate":null,"LastUpdatedDate":null,"IsDeleted":false,"DeletedDate":null,"IsArchived":false,"ArchivedDate":null}],"AnalysisId":null,"Id":1837,"ProjectId":1051,"OwnerId":0,"Title":"NC","DocumentKey":null,"UserWhoCreatedId":null,"UserWhoUpdatedId":1,"CreatedDate":"2018-06-04T12:12:53.61761Z","LastUpdatedDate":"2018-06-04T12:28:04.3541407Z","IsDeleted":false,"DeletedDate":null,"IsArchived":false,"ArchivedDate":null}]},"IsArchived":false,"ArchivedDateTime":null,"SharedDatetimes":[],"LastOpenedDate":"0001-01-01T00:00:00"}