{"Id":null,"DocumentKey":"","Project":{"Id":237,"DocumentKey":"","Title":"Created from regions","IndustrySetId":2,"CommoditySetId":1,"HouseholdSetId":1,"OwnerId":1,"HasImpacts":false,"HasResults":false,"LastOpened":null,"LastImpactRunId":null,"UserWhoCreatedId":1,"UserWhoUpdatedId":1,"CreatedDate":"2018-04-13T12:07:59","LastUpdatedDate":"2018-04-13T12:07:59","IsDeleted":false,"DeletedDate":null,"IsArchived":false,"ArchivedDate":null},"Analyses":[],"Impact":{"Name":"Impact from Regions","ProjectId":237,"Events":[],"Groups":[{"ModelId":-1914219503,"Year":19,"Events":[],"AnalysisId":null,"Id":427,"ProjectId":237,"OwnerId":0,"Title":"Virginia group","DocumentKey":"","UserWhoCreatedId":1,"UserWhoUpdatedId":1,"CreatedDate":"2018-04-13T12:07:59.4465159Z","LastUpdatedDate":"2018-04-13T12:07:59.446516Z","IsDeleted":false,"DeletedDate":null,"IsArchived":false,"ArchivedDate":null}]},"IsArchived":false,"ArchivedDateTime":null,"SharedDatetimes":[],"LastOpenedDate":"0001-01-01T00:00:00"}