{"Id":null,"DocumentKey":"","Project":{"Id":736,"DocumentKey":null,"Title":null,"IndustrySetId":0,"CommoditySetId":0,"HouseholdSetId":0,"OwnerId":0,"HasImpacts":false,"HasResults":false,"LastOpened":null,"LastImpactRunId":null,"UserWhoCreatedId":null,"UserWhoUpdatedId":null,"CreatedDate":null,"LastUpdatedDate":null,"IsDeleted":false,"DeletedDate":null,"IsArchived":false,"ArchivedDate":null},"Analyses":[],"Impact":{"Name":null,"ProjectId":736,"Events":[{"SpecificationCode":5001,"EventType":6,"Output":null,"Employment":null,"EmployeeCompensation":1000000.0,"ProprietorIncome":null,"Margins":false,"GdpDeflator":null,"OutputDeflator":null,"LocalPurchasePercentage":1.0,"OverideValidationWarning":false,"HouseholdIncome":null,"Id":1144,"ProjectId":736,"OwnerId":0,"Title":"evn1","DocumentKey":null,"UserWhoCreatedId":1,"UserWhoUpdatedId":1,"CreatedDate":"2018-05-09T04:28:28.558171Z","LastUpdatedDate":"2018-05-09T04:28:28.5581714Z","IsDeleted":false,"DeletedDate":null,"IsArchived":false,"ArchivedDate":null}],"Groups":[{"ModelId":34,"Year":38,"Events":[{"SpecificationCode":5001,"EventType":6,"Output":null,"Employment":null,"EmployeeCompensation":1000000.0,"ProprietorIncome":null,"Margins":false,"GdpDeflator":null,"OutputDeflator":null,"LocalPurchasePercentage":1.0,"OverideValidationWarning":false,"HouseholdIncome":null,"Id":1144,"ProjectId":736,"OwnerId":0,"Title":"evn1","DocumentKey":null,"UserWhoCreatedId":null,"UserWhoUpdatedId":null,"CreatedDate":null,"LastUpdatedDate":null,"IsDeleted":false,"DeletedDate":null,"IsArchived":false,"ArchivedDate":null}],"AnalysisId":null,"Id":1390,"ProjectId":736,"OwnerId":0,"Title":"grp1","DocumentKey":null,"UserWhoCreatedId":1,"UserWhoUpdatedId":1,"CreatedDate":"2018-05-09T04:28:28.5581719Z","LastUpdatedDate":"2018-05-09T04:28:28.5581722Z","IsDeleted":false,"DeletedDate":null,"IsArchived":false,"ArchivedDate":null}]},"IsArchived":false,"ArchivedDateTime":null,"SharedDatetimes":[],"LastOpenedDate":"0001-01-01T00:00:00"}