{"Id":null,"DocumentKey":"93e29899334e229fb340f5363d855b177a40e2be","Project":{"Id":1030,"DocumentKey":null,"Title":null,"IndustrySetId":0,"CommoditySetId":0,"HouseholdSetId":0,"OwnerId":0,"HasImpacts":false,"HasResults":false,"LastOpened":null,"LastImpactRunId":null,"UserWhoCreatedId":null,"UserWhoUpdatedId":null,"CreatedDate":null,"LastUpdatedDate":null,"IsDeleted":false,"DeletedDate":null,"IsArchived":false,"ArchivedDate":null},"Analyses":[],"Impact":{"Name":null,"ProjectId":1030,"Events":[{"SpecificationCode":395,"EventType":3,"Output":null,"Employment":null,"EmployeeCompensation":1000000.0,"ProprietorIncome":null,"Margins":false,"GdpDeflator":null,"OutputDeflator":null,"LocalPurchasePercentage":1.0,"OverideValidationWarning":false,"HouseholdIncome":null,"Id":1760,"ProjectId":1030,"OwnerId":0,"Title":"EmpComp_395_A","DocumentKey":null,"UserWhoCreatedId":null,"UserWhoUpdatedId":1,"CreatedDate":null,"LastUpdatedDate":"2018-06-01T10:21:26.945147Z","IsDeleted":false,"DeletedDate":null,"IsArchived":false,"ArchivedDate":null}],"Groups":[{"ModelId":85,"Year":38,"Events":[{"SpecificationCode":395,"EventType":3,"Output":null,"Employment":null,"EmployeeCompensation":1000000.0,"ProprietorIncome":null,"Margins":false,"GdpDeflator":null,"OutputDeflator":null,"LocalPurchasePercentage":1.0,"OverideValidationWarning":false,"HouseholdIncome":null,"Id":1760,"ProjectId":1030,"OwnerId":0,"Title":"EmpComp_395_A","DocumentKey":null,"UserWhoCreatedId":null,"UserWhoUpdatedId":null,"CreatedDate":null,"LastUpdatedDate":null,"IsDeleted":false,"DeletedDate":null,"IsArchived":false,"ArchivedDate":null}],"AnalysisId":null,"Id":1814,"ProjectId":1030,"OwnerId":0,"Title":"California-CA","DocumentKey":null,"UserWhoCreatedId":null,"UserWhoUpdatedId":1,"CreatedDate":"2018-06-01T10:04:48.1523167Z","LastUpdatedDate":"2018-06-01T10:21:26.9451476Z","IsDeleted":false,"DeletedDate":null,"IsArchived":false,"ArchivedDate":null}]},"IsArchived":false,"ArchivedDateTime":null,"SharedDatetimes":[],"LastOpenedDate":"0001-01-01T00:00:00"}