{
  "Id": null,
  "DocumentKey": "855ad98bf7cf3a993715de0a63fb3195a9bebb0b",
  "Project": {
    "Id": 1324,
    "DocumentKey": null,
    "Title": null,
    "IndustrySetId": 0,
    "CommoditySetId": 0,
    "HouseholdSetId": 0,
    "OwnerId": 0,
    "HasImpacts": false,
    "HasResults": false,
    "LastOpened": null,
    "LastImpactRunId": null,
    "UserWhoCreatedId": null,
    "UserWhoUpdatedId": null,
    "CreatedDate": null,
    "LastUpdatedDate": null,
    "IsDeleted": false,
    "DeletedDate": null,
    "IsArchived": false,
    "ArchivedDate": null
  },
  "Analyses": [],
  "Impact": {
    "Name": null,
    "ProjectId": 1324,
    "Events": [
      {
        "SpecificationCode": 0,
        "EventType": 0,
        "Output": null,
        "Employment": null,
        "EmployeeCompensation": null,
        "ProprietorIncome": null,
        "Margins": false,
        "GdpDeflator": null,
        "OutputDeflator": null,
        "LocalPurchasePercentage": 1.0,
        "OverideValidationWarning": false,
        "HouseholdIncome": null,
        "Id": 2323,
        "ProjectId": 1324,
        "OwnerId": 0,
        "Title": "",
        "DocumentKey": null,
        "UserWhoCreatedId": null,
        "UserWhoUpdatedId": 1,
        "CreatedDate": null,
        "LastUpdatedDate": "2018-06-26T11:04:14.0108045Z",
        "IsDeleted": false,
        "DeletedDate": null,
        "IsArchived": false,
        "ArchivedDate": null
      },
      {
        "SpecificationCode": 0,
        "EventType": 0,
        "Output": null,
        "Employment": null,
        "EmployeeCompensation": null,
        "ProprietorIncome": null,
        "Margins": false,
        "GdpDeflator": null,
        "OutputDeflator": null,
        "LocalPurchasePercentage": 1.0,
        "OverideValidationWarning": false,
        "HouseholdIncome": null,
        "Id": 2324,
        "ProjectId": 1324,
        "OwnerId": 0,
        "Title": "",
        "DocumentKey": null,
        "UserWhoCreatedId": null,
        "UserWhoUpdatedId": 1,
        "CreatedDate": null,
        "LastUpdatedDate": "2018-06-26T11:04:14.0108049Z",
        "IsDeleted": false,
        "DeletedDate": null,
        "IsArchived": false,
        "ArchivedDate": null
      },
      {
        "SpecificationCode": 0,
        "EventType": 0,
        "Output": null,
        "Employment": null,
        "EmployeeCompensation": null,
        "ProprietorIncome": null,
        "Margins": false,
        "GdpDeflator": null,
        "OutputDeflator": null,
        "LocalPurchasePercentage": 1.0,
        "OverideValidationWarning": false,
        "HouseholdIncome": null,
        "Id": 2325,
        "ProjectId": 1324,
        "OwnerId": 0,
        "Title": "",
        "DocumentKey": null,
        "UserWhoCreatedId": null,
        "UserWhoUpdatedId": 1,
        "CreatedDate": null,
        "LastUpdatedDate": "2018-06-26T11:04:14.0108052Z",
        "IsDeleted": false,
        "DeletedDate": null,
        "IsArchived": false,
        "ArchivedDate": null
      }
    ],
    "Groups": [
      {
        "ModelId": 166,
        "Year": 38,
        "Events": [],
        "AnalysisId": null,
        "Id": 2348,
        "ProjectId": 1324,
        "OwnerId": 0,
        "Title": "Pennsylvania group",
        "DocumentKey": null,
        "UserWhoCreatedId": null,
        "UserWhoUpdatedId": 1,
        "CreatedDate": "2018-06-26T11:03:49.8150409Z",
        "LastUpdatedDate": "2018-06-26T11:04:14.0108056Z",
        "IsDeleted": false,
        "DeletedDate": null,
        "IsArchived": false,
        "ArchivedDate": null
      },
      {
        "ModelId": null,
        "Year": null,
        "Events": [],
        "AnalysisId": null,
        "Id": 2349,
        "ProjectId": 1324,
        "OwnerId": 0,
        "Title": "",
        "DocumentKey": null,
        "UserWhoCreatedId": null,
        "UserWhoUpdatedId": 1,
        "CreatedDate": null,
        "LastUpdatedDate": "2018-06-26T11:04:14.0108059Z",
        "IsDeleted": false,
        "DeletedDate": null,
        "IsArchived": false,
        "ArchivedDate": null
      },
      {
        "ModelId": null,
        "Year": null,
        "Events": [],
        "AnalysisId": null,
        "Id": 2350,
        "ProjectId": 1324,
        "OwnerId": 0,
        "Title": "",
        "DocumentKey": null,
        "UserWhoCreatedId": null,
        "UserWhoUpdatedId": 1,
        "CreatedDate": null,
        "LastUpdatedDate": "2018-06-26T11:04:14.0108062Z",
        "IsDeleted": false,
        "DeletedDate": null,
        "IsArchived": false,
        "ArchivedDate": null
      },
      {
        "ModelId": null,
        "Year": null,
        "Events": [],
        "AnalysisId": null,
        "Id": 2351,
        "ProjectId": 1324,
        "OwnerId": 0,
        "Title": "",
        "DocumentKey": null,
        "UserWhoCreatedId": null,
        "UserWhoUpdatedId": 1,
        "CreatedDate": null,
        "LastUpdatedDate": "2018-06-26T11:04:14.0108065Z",
        "IsDeleted": false,
        "DeletedDate": null,
        "IsArchived": false,
        "ArchivedDate": null
      },
      {
        "ModelId": null,
        "Year": null,
        "Events": [],
        "AnalysisId": null,
        "Id": 2352,
        "ProjectId": 1324,
        "OwnerId": 0,
        "Title": "",
        "DocumentKey": null,
        "UserWhoCreatedId": null,
        "UserWhoUpdatedId": 1,
        "CreatedDate": null,
        "LastUpdatedDate": "2018-06-26T11:04:14.0108069Z",
        "IsDeleted": false,
        "DeletedDate": null,
        "IsArchived": false,
        "ArchivedDate": null
      },
      {
        "ModelId": null,
        "Year": null,
        "Events": [],
        "AnalysisId": null,
        "Id": 2353,
        "ProjectId": 1324,
        "OwnerId": 0,
        "Title": "",
        "DocumentKey": null,
        "UserWhoCreatedId": null,
        "UserWhoUpdatedId": 1,
        "CreatedDate": null,
        "LastUpdatedDate": "2018-06-26T11:04:14.0108072Z",
        "IsDeleted": false,
        "DeletedDate": null,
        "IsArchived": false,
        "ArchivedDate": null
      }
    ]
  },
  "IsArchived": false,
  "ArchivedDateTime": null,
  "SharedDatetimes": [],
  "LastOpenedDate": "0001-01-01T00:00:00"
}