{"Id":null,"DocumentKey":"","Project":{"Id":269,"DocumentKey":"","Title":"Created from regions","IndustrySetId":2,"CommoditySetId":1,"HouseholdSetId":1,"OwnerId":1,"HasImpacts":false,"HasResults":false,"LastOpened":null,"LastImpactRunId":null,"UserWhoCreatedId":1,"UserWhoUpdatedId":1,"CreatedDate":"2018-04-16T04:00:19","LastUpdatedDate":"2018-04-16T04:00:19","IsDeleted":false,"DeletedDate":null,"IsArchived":false,"ArchivedDate":null},"Analyses":[],"Impact":{"Name":"Impact from Regions","ProjectId":269,"Events":[],"Groups":[{"ModelId":-315239098,"Year":19,"Events":[],"AnalysisId":null,"Id":652,"ProjectId":269,"OwnerId":0,"Title":"Florida group","DocumentKey":"","UserWhoCreatedId":1,"UserWhoUpdatedId":1,"CreatedDate":"2018-04-16T04:00:19.7341078Z","LastUpdatedDate":"2018-04-16T04:00:19.734108Z","IsDeleted":false,"DeletedDate":null,"IsArchived":false,"ArchivedDate":null}]},"IsArchived":false,"ArchivedDateTime":null,"SharedDatetimes":[],"LastOpenedDate":"0001-01-01T00:00:00"}