{"Id":26,"Key":"","Project":{"Id":26,"DocumentKey":"","Title":"Project from Regions","IndustrySetId":2,"CommoditySetId":1,"HouseholdSetId":1,"OwnerId":1,"HasImpacts":false,"HasResults":false,"LastOpened":null,"UserWhoCreatedId":1,"UserWhoUpdatedId":1,"CreatedDate":"2018-03-27T14:27:58","LastUpdatedDate":"2018-03-27T14:27:58","IsDeleted":false,"DeletedDate":null,"IsArchived":false,"ArchivedDate":null},"Analyses":[],"Impact":{"Name":"Impact from Regions","ProjectId":26,"Events":[],"Groups":[{"Id":null,"ProjectId":26,"Title":"Louisiana group","ModelId":null,"Year":null,"Events":[],"AnalysisId":null,"UserWhoCreatedId":1,"UserWhoUpdatedId":1,"CreatedDate":"2018-03-27T14:27:59.0655091Z","LastUpdatedDate":"2018-03-27T14:27:59.0655093Z","IsDeleted":false,"DeletedDate":null,"IsArchived":false,"ArchivedDate":null},{"Id":null,"ProjectId":26,"Title":"Mississippi group","ModelId":null,"Year":null,"Events":[],"AnalysisId":null,"UserWhoCreatedId":1,"UserWhoUpdatedId":1,"CreatedDate":"2018-03-27T14:27:59.0655119Z","LastUpdatedDate":"2018-03-27T14:27:59.065512Z","IsDeleted":false,"DeletedDate":null,"IsArchived":false,"ArchivedDate":null}]},"IsArchived":false,"ArchivedDateTime":null,"SharedDatetimes":[],"LastOpenedDate":"0001-01-01T00:00:00"}