{
  "Id": null,
  "DocumentKey": "0fee5133947c40ead6ec8a3a7db309a5602ca865",
  "Project": {
    "Id": 1330,
    "DocumentKey": null,
    "Title": null,
    "IndustrySetId": 0,
    "CommoditySetId": 0,
    "HouseholdSetId": 0,
    "OwnerId": 0,
    "HasImpacts": false,
    "HasResults": false,
    "LastOpened": null,
    "LastImpactRunId": null,
    "UserWhoCreatedId": null,
    "UserWhoUpdatedId": null,
    "CreatedDate": null,
    "LastUpdatedDate": null,
    "IsDeleted": false,
    "DeletedDate": null,
    "IsArchived": false,
    "ArchivedDate": null
  },
  "Analyses": [],
  "Impact": {
    "Name": null,
    "ProjectId": 1330,
    "Events": [
      {
        "SpecificationCode": 518,
        "EventType": 1,
        "Output": 1500000.0,
        "Employment": null,
        "EmployeeCompensation": null,
        "ProprietorIncome": null,
        "Margins": null,
        "GdpDeflator": null,
        "OutputDeflator": null,
        "LocalPurchasePercentage": 1.0,
        "OverideValidationWarning": false,
        "HouseholdIncome": null,
        "Id": 2341,
        "ProjectId": 1330,
        "OwnerId": 0,
        "Title": "IO_518_V2_A",
        "DocumentKey": null,
        "UserWhoCreatedId": null,
        "UserWhoUpdatedId": 1,
        "CreatedDate": null,
        "LastUpdatedDate": "2018-06-27T06:50:19.7760435Z",
        "IsDeleted": false,
        "DeletedDate": null,
        "IsArchived": false,
        "ArchivedDate": null
      }
    ],
    "Groups": [
      {
        "ModelId": 209,
        "Year": 38,
        "Events": [
          {
            "SpecificationCode": 518,
            "EventType": 1,
            "Output": 1500000.0,
            "Employment": null,
            "EmployeeCompensation": null,
            "ProprietorIncome": null,
            "Margins": null,
            "GdpDeflator": null,
            "OutputDeflator": null,
            "LocalPurchasePercentage": 1.0,
            "OverideValidationWarning": false,
            "HouseholdIncome": null,
            "Id": 2341,
            "ProjectId": 1330,
            "OwnerId": 0,
            "Title": "IO_518_V2_A",
            "DocumentKey": null,
            "UserWhoCreatedId": null,
            "UserWhoUpdatedId": null,
            "CreatedDate": null,
            "LastUpdatedDate": null,
            "IsDeleted": false,
            "DeletedDate": null,
            "IsArchived": false,
            "ArchivedDate": null
          }
        ],
        "AnalysisId": null,
        "Id": 2360,
        "ProjectId": 1330,
        "OwnerId": 0,
        "Title": "NC+York_SC",
        "DocumentKey": null,
        "UserWhoCreatedId": null,
        "UserWhoUpdatedId": 1,
        "CreatedDate": "2018-06-27T06:41:52.7267341Z",
        "LastUpdatedDate": "2018-06-27T06:50:19.7760439Z",
        "IsDeleted": false,
        "DeletedDate": null,
        "IsArchived": false,
        "ArchivedDate": null
      }
    ]
  },
  "IsArchived": false,
  "ArchivedDateTime": null,
  "SharedDatetimes": [],
  "LastOpenedDate": "0001-01-01T00:00:00"
}