{"Id":null,"DocumentKey":"7d5b7394c449fc2fc980164896d2cf1045013663","Project":{"Id":1016,"DocumentKey":null,"Title":null,"IndustrySetId":0,"CommoditySetId":0,"HouseholdSetId":0,"OwnerId":0,"HasImpacts":false,"HasResults":false,"LastOpened":null,"LastImpactRunId":null,"UserWhoCreatedId":null,"UserWhoUpdatedId":null,"CreatedDate":null,"LastUpdatedDate":null,"IsDeleted":false,"DeletedDate":null,"IsArchived":false,"ArchivedDate":null},"Analyses":[],"Impact":{"Name":null,"ProjectId":1016,"Events":[{"SpecificationCode":10007,"EventType":7,"Output":null,"Employment":null,"EmployeeCompensation":null,"ProprietorIncome":null,"Margins":false,"GdpDeflator":null,"OutputDeflator":null,"LocalPurchasePercentage":1.0,"OverideValidationWarning":false,"HouseholdIncome":1000000.0,"Id":1731,"ProjectId":1016,"OwnerId":0,"Title":"HH_100-150k_Agg","DocumentKey":null,"UserWhoCreatedId":null,"UserWhoUpdatedId":1,"CreatedDate":null,"LastUpdatedDate":"2018-05-31T10:25:50.5377736Z","IsDeleted":false,"DeletedDate":null,"IsArchived":false,"ArchivedDate":null}],"Groups":[{"ModelId":80,"Year":38,"Events":[{"SpecificationCode":10007,"EventType":7,"Output":null,"Employment":null,"EmployeeCompensation":null,"ProprietorIncome":null,"Margins":false,"GdpDeflator":null,"OutputDeflator":null,"LocalPurchasePercentage":1.0,"OverideValidationWarning":false,"HouseholdIncome":1000000.0,"Id":1731,"ProjectId":1016,"OwnerId":0,"Title":"HH_100-150k_Agg","DocumentKey":null,"UserWhoCreatedId":null,"UserWhoUpdatedId":null,"CreatedDate":null,"LastUpdatedDate":null,"IsDeleted":false,"DeletedDate":null,"IsArchived":false,"ArchivedDate":null}],"AnalysisId":null,"Id":1793,"ProjectId":1016,"OwnerId":0,"Title":"Washington-MN","DocumentKey":null,"UserWhoCreatedId":null,"UserWhoUpdatedId":1,"CreatedDate":"2018-05-31T10:23:13.7565652Z","LastUpdatedDate":"2018-05-31T10:25:50.5377759Z","IsDeleted":false,"DeletedDate":null,"IsArchived":false,"ArchivedDate":null}]},"IsArchived":false,"ArchivedDateTime":null,"SharedDatetimes":[],"LastOpenedDate":"0001-01-01T00:00:00"}