{
  "Id": null,
  "DocumentKey": "51846f8b4115be1d8d4f683cf6b0ebd83fcb096a",
  "Project": {
    "Id": 1543,
    "DocumentKey": null,
    "Title": null,
    "IndustrySetId": 0,
    "CommoditySetId": 0,
    "HouseholdSetId": 0,
    "OwnerId": 0,
    "HasImpacts": false,
    "HasResults": false,
    "LastOpened": null,
    "LastImpactRunId": null,
    "UserWhoCreatedId": null,
    "UserWhoUpdatedId": null,
    "CreatedDate": null,
    "LastUpdatedDate": null,
    "IsDeleted": false,
    "DeletedDate": null,
    "IsArchived": false,
    "ArchivedDate": null
  },
  "Analyses": [],
  "Impact": {
    "Name": null,
    "ProjectId": 1543,
    "Events": [
      {
        "SpecificationCode": 5001,
        "EventType": 6,
        "Output": null,
        "Employment": 1000000.0,
        "EmployeeCompensation": 1000000.0,
        "ProprietorIncome": null,
        "Margins": false,
        "GdpDeflator": null,
        "OutputDeflator": null,
        "LocalPurchasePercentage": 1.0,
        "OverideValidationWarning": false,
        "HouseholdIncome": null,
        "Id": 2662,
        "ProjectId": 1543,
        "OwnerId": 0,
        "Title": "Test2",
        "DocumentKey": null,
        "UserWhoCreatedId": null,
        "UserWhoUpdatedId": 14,
        "CreatedDate": null,
        "LastUpdatedDate": "2018-07-16T09:22:48.7498557Z",
        "IsDeleted": false,
        "DeletedDate": null,
        "IsArchived": false,
        "ArchivedDate": null
      }
    ],
    "Groups": [
      {
        "ModelId": 252,
        "Year": 39,
        "Events": [
          {
            "SpecificationCode": 5001,
            "EventType": 6,
            "Output": null,
            "Employment": 1000000.0,
            "EmployeeCompensation": 1000000.0,
            "ProprietorIncome": null,
            "Margins": false,
            "GdpDeflator": null,
            "OutputDeflator": null,
            "LocalPurchasePercentage": 1.0,
            "OverideValidationWarning": false,
            "HouseholdIncome": null,
            "Id": 2662,
            "ProjectId": 1543,
            "OwnerId": 0,
            "Title": "Test2",
            "DocumentKey": null,
            "UserWhoCreatedId": null,
            "UserWhoUpdatedId": 14,
            "CreatedDate": null,
            "LastUpdatedDate": "2018-07-16T07:32:13.8959556Z",
            "IsDeleted": false,
            "DeletedDate": null,
            "IsArchived": false,
            "ArchivedDate": null
          }
        ],
        "AnalysisId": null,
        "Id": 2771,
        "ProjectId": 1543,
        "OwnerId": 0,
        "Title": "Grp1",
        "DocumentKey": null,
        "UserWhoCreatedId": null,
        "UserWhoUpdatedId": 14,
        "CreatedDate": "2018-07-16T07:30:52.5936493Z",
        "LastUpdatedDate": "2018-07-16T09:22:48.7498562Z",
        "IsDeleted": false,
        "DeletedDate": null,
        "IsArchived": false,
        "ArchivedDate": null
      }
    ]
  },
  "IsArchived": false,
  "ArchivedDateTime": null,
  "SharedDatetimes": [],
  "LastOpenedDate": "0001-01-01T00:00:00"
}