{
  "Id": null,
  "DocumentKey": "a79d282356f80f5bab76589e83ae03df2982a5a7",
  "Project": {
    "Id": 1256,
    "DocumentKey": null,
    "Title": null,
    "IndustrySetId": 0,
    "CommoditySetId": 0,
    "HouseholdSetId": 0,
    "OwnerId": 0,
    "HasImpacts": false,
    "HasResults": false,
    "LastOpened": null,
    "LastImpactRunId": null,
    "UserWhoCreatedId": null,
    "UserWhoUpdatedId": null,
    "CreatedDate": null,
    "LastUpdatedDate": null,
    "IsDeleted": false,
    "DeletedDate": null,
    "IsArchived": false,
    "ArchivedDate": null
  },
  "Analyses": [],
  "Impact": {
    "Name": null,
    "ProjectId": 1256,
    "Events": [
      {
        "SpecificationCode": 1,
        "EventType": 1,
        "Output": 1000000.0,
        "Employment": null,
        "EmployeeCompensation": null,
        "ProprietorIncome": null,
        "Margins": null,
        "GdpDeflator": null,
        "OutputDeflator": null,
        "LocalPurchasePercentage": 1.0,
        "OverideValidationWarning": false,
        "HouseholdIncome": null,
        "Id": 2192,
        "ProjectId": 1256,
        "OwnerId": 0,
        "Title": "IO_1_A",
        "DocumentKey": null,
        "UserWhoCreatedId": null,
        "UserWhoUpdatedId": 1,
        "CreatedDate": null,
        "LastUpdatedDate": "2018-06-20T07:19:56.3457503Z",
        "IsDeleted": false,
        "DeletedDate": null,
        "IsArchived": false,
        "ArchivedDate": null
      }
    ],
    "Groups": [
      {
        "ModelId": 206,
        "Year": 38,
        "Events": [
          {
            "SpecificationCode": 1,
            "EventType": 1,
            "Output": 1000000.0,
            "Employment": null,
            "EmployeeCompensation": null,
            "ProprietorIncome": null,
            "Margins": null,
            "GdpDeflator": null,
            "OutputDeflator": null,
            "LocalPurchasePercentage": 1.0,
            "OverideValidationWarning": false,
            "HouseholdIncome": null,
            "Id": 2192,
            "ProjectId": 1256,
            "OwnerId": 0,
            "Title": "IO_1_A",
            "DocumentKey": null,
            "UserWhoCreatedId": null,
            "UserWhoUpdatedId": null,
            "CreatedDate": null,
            "LastUpdatedDate": null,
            "IsDeleted": false,
            "DeletedDate": null,
            "IsArchived": false,
            "ArchivedDate": null
          }
        ],
        "AnalysisId": null,
        "Id": 2251,
        "ProjectId": 1256,
        "OwnerId": 0,
        "Title": "Washington-MN",
        "DocumentKey": null,
        "UserWhoCreatedId": null,
        "UserWhoUpdatedId": 1,
        "CreatedDate": "2018-06-19T23:21:18.3802701Z",
        "LastUpdatedDate": "2018-06-20T07:19:56.3457509Z",
        "IsDeleted": false,
        "DeletedDate": null,
        "IsArchived": false,
        "ArchivedDate": null
      }
    ]
  },
  "IsArchived": false,
  "ArchivedDateTime": null,
  "SharedDatetimes": [],
  "LastOpenedDate": "0001-01-01T00:00:00"
}