{
  "Id": null,
  "DocumentKey": "61f350ecbbc43858cd748eba6e2562bad0b57a62",
  "Project": {
    "Id": 1371,
    "DocumentKey": null,
    "Title": null,
    "IndustrySetId": 0,
    "CommoditySetId": 0,
    "HouseholdSetId": 0,
    "OwnerId": 0,
    "HasImpacts": false,
    "HasResults": false,
    "LastOpened": null,
    "LastImpactRunId": null,
    "UserWhoCreatedId": null,
    "UserWhoUpdatedId": null,
    "CreatedDate": null,
    "LastUpdatedDate": null,
    "IsDeleted": false,
    "DeletedDate": null,
    "IsArchived": false,
    "ArchivedDate": null
  },
  "Analyses": [],
  "Impact": {
    "Name": null,
    "ProjectId": 1371,
    "Events": [],
    "Groups": [
      {
        "ModelId": null,
        "Year": 39,
        "Events": [],
        "AnalysisId": null,
        "Id": 2417,
        "ProjectId": 1371,
        "OwnerId": 0,
        "Title": "Nebraska group",
        "DocumentKey": null,
        "UserWhoCreatedId": null,
        "UserWhoUpdatedId": 13,
        "CreatedDate": "2018-07-02T09:50:01.4357509Z",
        "LastUpdatedDate": "2018-07-03T05:39:06.5483038Z",
        "IsDeleted": false,
        "DeletedDate": null,
        "IsArchived": false,
        "ArchivedDate": null
      }
    ]
  },
  "IsArchived": false,
  "ArchivedDateTime": null,
  "SharedDatetimes": [],
  "LastOpenedDate": "0001-01-01T00:00:00"
}